mobi/__init__.py
mobi/lz77.py
mobi/utils.py
mobi_python-0.0.1.dist-info/LICENCE
mobi_python-0.0.1.dist-info/METADATA
mobi_python-0.0.1.dist-info/WHEEL
mobi_python-0.0.1.dist-info/top_level.txt
mobi_python-0.0.1.dist-info/RECORD
