Metadata-Version: 2.1
Name: mobi-python
Version: 0.0.1
Summary: Mobi Python Library
Home-page: https://github.com/kroo/mobi-python
Author: Elliot Kroo
Author-email: elliot@kroo.net
License: UNKNOWN
Platform: UNKNOWN
Classifier: Programming Language :: Python :: 3
Classifier: License :: OSI Approved :: MIT License
Classifier: Operating System :: OS Independent
